ebsi_wallet/__init__.py
ebsi_wallet/did_jwt/__init__.py
ebsi_wallet/did_jwt/signer_algorithm.py
ebsi_wallet/did_jwt/util/__init__.py
ebsi_wallet/did_jwt/util/json_canonicalize/Canonicalize.py
ebsi_wallet/did_jwt/util/json_canonicalize/NumberToJson.py
ebsi_wallet/did_jwt/util/json_canonicalize/__init__.py
ebsi_wallet/did_key/__init__.py
ebsi_wallet/ebsi_client/__init__.py
ebsi_wallet/ebsi_did/__init__.py
ebsi_wallet/ebsi_did_resolver/__init__.py
ebsi_wallet/ebsi_did_resolver/constants/__init__.py
ebsi_wallet/ebsi_did_resolver/validators/__init__.py
ebsi_wallet/ethereum/__init__.py
ebsi_wallet/ethereum/util.py
ebsi_wallet/main.py
ebsi_wallet/siop_auth/__init__.py
ebsi_wallet/siop_auth/util.py
ebsi_wallet/util/__init__.py
ebsi_wallet/util/verifiable_presentation.py
ebsi_wallet/validators/__init__.py
ebsi_wallet/verifiable_credential/__init__.py
ebsi_wallet/verifiable_credential/validators/__init__.py
ebsi_wallet/verifiable_presentation/__init__.py
ebsi_wallet/verifiable_presentation/v2/__init__.py
ebsi_wallet-0.1.3.dist-info/LICENSE
ebsi_wallet-0.1.3.dist-info/WHEEL
ebsi_wallet-0.1.3.dist-info/METADATA
ebsi_wallet-0.1.3.dist-info/RECORD
